dasstore/__init__.py
dasstore/_version.py
dasstore/tiledb/__init__.py
dasstore/tiledb/client.py
dasstore/utils/__init__.py
dasstore/utils/convert.py
dasstore/utils/credential.py
dasstore/zarr/__init__.py
dasstore/zarr/client.py
dasstore-0.2.2.dist-info/METADATA
dasstore-0.2.2.dist-info/WHEEL
dasstore-0.2.2.dist-info/licenses/LICENSE
dasstore-0.2.2.dist-info/RECORD
