Metadata-Version: 2.3
Name: dasstore
Version: 0.2.2
Summary: An Object Storage for Distributed Acoustic Sensing
Project-URL: Homepage, https://github.com/niyiyu/dasstore
Author-email: Yiyu Ni <niyiyu@uw.edu>
License:                     GNU GENERAL PUBLIC LICENSE
License-File: LICENSE
Keywords: cloud-storage,data,distributed-acoustic-sensing,minio,object-storage,s3,seismology
Classifier: Environment :: Console
Classifier: Intended Audience :: Developers
Classifier: Intended Audience :: Science/Research
Classifier: Operating System :: OS Independent
Classifier: Programming Language :: Python :: 3.8
Requires-Python: <3.11,>=3.8
Requires-Dist: fsspec<2024.0.0,>=2023.4.0
Requires-Dist: numpy<2.0.0
Requires-Dist: pandas<2.0.0,>=1.5.3
Requires-Dist: s3fs<2024.0.0,==2023.4.0
Requires-Dist: tiledb==0.23.0
Requires-Dist: zarr==2.14.2
Provides-Extra: dev
Requires-Dist: memory-profiler==0.61; extra == 'dev'
Requires-Dist: pre-commit==3.3.3; extra == 'dev'
Requires-Dist: pytest-cov==4.1.0; extra == 'dev'
Requires-Dist: pytest==7.2.2; extra == 'dev'
